axcli/__init__.py
axcli/__main__.py
axcli/_list.py
axcli/catalog.py
axcli/cli.py
axcli/live.py
axcli/load.py
axcli/menu.py
axcli/read.py
axcli/run.py
axcli/show.py
axcli-1.3.0.dist-info/LICENSE.md
axcli-1.3.0.dist-info/METADATA
axcli-1.3.0.dist-info/WHEEL
axcli-1.3.0.dist-info/entry_points.txt
axcli-1.3.0.dist-info/top_level.txt
axcli-1.3.0.dist-info/RECORD
