Metadata-Version: 2.2
Name: axcli
Version: 1.3.0
Summary: A command line interface for the Axinite library.
Author-email: Jewels <jewels@jewels86.me>
Maintainer-email: Jewels <jewels286@proton.me>
License:                     GNU GENERAL PUBLIC LICENSE
Project-URL: Documentation, https://jewels86.gitbook.io/axinite/axcli
Project-URL: Repository, https://github.com/jewels86/axcli
Keywords: celestial-mechanics,orbital-dynamics,engine,astrodynamics,cli
License-File: LICENSE.md
Requires-Dist: axinite
Requires-Dist: click
Requires-Dist: colorama
